{
    "translations": {
        "de": {
            "Garbage Types": "Müllarten",
            "Notifications": "Benachrichtigungen",
            "HTML Settings": "HTML-Einstellungen",
            "Select garbage type:": "Müllarten auswählen:",
            "Yellow bag": "Gelber Sack",
            "Yellow bag event": "Gelber Sack Termin",
            "Household garbage": "Hausmüll",
            "Household garbage event": "Hausmüll Termin",
            "Cardboard bin": "Pappetonne",
            "Cardboard bin event": "Pappetonne Termin",
            "Organic waste": "Biomüll",
            "Organic waste event": "Biomüll Termin",
            "Push Notification:": "Push-Benachrichtigung",
            "ID for push notifications": "ID für Push-Benachrichtigung",
            "E-Mail notification:": "E-Mail-Benachrichtigung",
            "ID for E-Mail notification:": "ID für E-Mail-Benachrichtigung",
            "Specification of the hour for the update timer": "Angabe der Stunde für Update-Timer",
            "Specification of the hour for the notification timer": "Angabe der Stunde für Notification-Timer",
            "Hour": "Stunde",
            "Minute": "Minute",
            "HTML font size": "HTML-Schriftgröße",
            "Show day of week in HTML output": "Wochentag in HTML-Output anzeigen",
            "HTML default font color": "Standardfarbe HTML Output",
            "HTML pickupday font color for tomorrow": "HTML-Farbe für morgigen Abfuhrtermin",
            "HTML pickupday font color for today": "HTML-Farbe für heutigen Abfuhrtermin",
            "Update Garbage collection appointments": "Update Abfuhrtermine",
            "Set demo data" :"Demodaten setzen",
            "Module is functional. It may be necessary to import demo data once" :"Modul ist funktionsfähig. GGf. müssen Demodaten einmalig importiert werden",
            "Module is functional" :"Modul ist funktionsfähig",
            "At least one appointment variable is empty. Please deactivate it in the instance settings!": "Mindestens eine Termin-Variable ist leer. Bitte diese in den Instance-Settings deaktivieren!",
            "The indication of the hour for the timer must be set in the range between 0-23!": "Die Angabe der Stunde für die Timer müssen im Bereich zwischen 0-23 gesetzt sein!",
            "Waste dates": "Abfalltermine",
            "The hour of a time is wrong!": "Die Stunde einer Zeitangabe ist falsch!",
            "Starting updates of waste times.": "Starte Update der Abfalltermine.",
            "One or more of the waste time strings are empty!": "Einer oder mehrere Abfalltermine-Strings sind leer!",
            "TOMORROW": "MORGEN",
            "TODAY": "HEUTE",
            "Push notification is sending now.": "Push-Benachrichtigung wird gesendet.",
            "Mail notification is sending now.": "Mail-Benachrichtigung wird gesendet.",
            "Tomorrow will ": "Morgen wird ",
            " picked up!": " abgeholt!",
            "Next update time: ": "Uhrzeit für nächstes Update: ",
            "Next notification time: ": "Uhrzeit für nächste Push-Benachrichtigung: ",
            "Demo data were successfully stored.": "Demodaten wurden erfolgreich hinterlegt.",
            "Seconds for next Timer ": "Sekunden bis zum nächsten Timer ",
            "Next milliseconds for timer ": "Millisekunden bis zum nächsten Timer ",
            " is ": " ist ",
            "Mon": "Mo",
            "Tue": "Di",
            "Wed": "Mi",
            "Thu": "Do",
            "Fri": "Fr",
            "Sat": "Sa",
            "Sun": "So"
        }
    }
}